xxcmd/__init__.py
xxcmd/__main__.py
xxcmd/cmdmanager.py
xxcmd/config.py
xxcmd/consoleui.py
xxcmd/dbitem.py
xxcmd/lineedit.py
xxcmd/main.py
xxcmd-0.10.1.dist-info/entry_points.txt
xxcmd-0.10.1.dist-info/LICENSE
xxcmd-0.10.1.dist-info/WHEEL
xxcmd-0.10.1.dist-info/METADATA
xxcmd-0.10.1.dist-info/RECORD
