Metadata-Version: 2.1
Name: xxcmd
Version: 0.10.1
Summary: A helper for remembering useful shell commands.
Home-page: https://github.com/grking/xxcmd
License: MIT License
Author: Graham R King
Author-email: grking.email@gmail.com
Requires-Python: >=3.2
Classifier: License :: OSI Approved :: MIT License
Classifier: Development Status :: 4 - Beta
Classifier: Environment :: Console :: Curses
Classifier: Natural Language :: English
Classifier: Programming Language :: Python :: 3
Classifier: Operating System :: POSIX
Classifier: Operating System :: POSIX :: Linux
